codey_cli/__init__.py
codey_cli/cli.py
codey_cli-0.1.3.dist-info/METADATA
codey_cli-0.1.3.dist-info/WHEEL
codey_cli-0.1.3.dist-info/entry_points.txt
codey_cli-0.1.3.dist-info/top_level.txt
codey_cli-0.1.3.dist-info/RECORD
