Metadata-Version: 2.4
Name: codey-cli
Version: 0.1.3
Summary: Save code agent conversations aligned with git commits.
Author: Joway
License-Expression: MIT
Requires-Python: >=3.8
